lofar_cryptocoryne/__init__.py
lofar_cryptocoryne/_version.py
lofar_cryptocoryne/cli.py
lofar_cryptocoryne/client.py
lofar_cryptocoryne/dns_client.py
lofar_cryptocoryne/storage.py
lofar_cryptocoryne-0.1.1.dist-info/LICENSE
lofar_cryptocoryne-0.1.1.dist-info/METADATA
lofar_cryptocoryne-0.1.1.dist-info/WHEEL
lofar_cryptocoryne-0.1.1.dist-info/entry_points.txt
lofar_cryptocoryne-0.1.1.dist-info/top_level.txt
lofar_cryptocoryne-0.1.1.dist-info/RECORD
