Metadata-Version: 2.2
Name: lofar-cryptocoryne
Version: 0.1.1
Summary: Automated certificate acquisition and renewal for nomad services
Home-page: https://git.astron.nl/lofar2.0/cryptocoryne
License: Apache License 2.0
Classifier: Development Status :: 3 - Alpha
Classifier: Environment :: No Input/Output (Daemon)
Classifier: Intended Audience :: Developers
Classifier: Intended Audience :: Science/Research
Classifier: License :: OSI Approved :: Apache Software License
Classifier: Operating System :: OS Independent
Classifier: Programming Language :: Python
Classifier: Programming Language :: Python :: 3
Classifier: Programming Language :: Python :: 3 :: Only
Classifier: Programming Language :: Python :: 3.9
Classifier: Programming Language :: Python :: 3.10
Classifier: Programming Language :: Python :: 3.11
Classifier: Programming Language :: Python :: 3.12
Classifier: Topic :: Security
Classifier: Topic :: Scientific/Engineering
Classifier: Topic :: Scientific/Engineering :: Astronomy
Requires-Python: >=3.9
License-File: LICENSE
Requires-Dist: hvac
Requires-Dist: py-consul
Requires-Dist: requests[socks]
Requires-Dist: acme
Requires-Dist: josepy
Requires-Dist: simple_acme_dns
Requires-Dist: cryptography
Requires-Dist: desec-dns
